{
  "persons":
      [{"id":1,"first_name":"Zara","last_name":"Thirkettle"},
{"id":2,"first_name":"Yetty","last_name":"Sighart"},
{"id":3,"first_name":"Nellie","last_name":"Cadle"},
{"id":4,"first_name":"Bryna","last_name":"Deering"},
{"id":5,"first_name":"Kristien","last_name":"Harridge"},
{"id":6,"first_name":"Grant","last_name":"Lyons"},
{"id":7,"first_name":"Kevina","last_name":"Kornalik"},
{"id":8,"first_name":"Eldridge","last_name":"Savaage"},
{"id":9,"first_name":"Allister","last_name":"Skippen"},
{"id":10,"first_name":"Fabio","last_name":"Beckford"},
{"id":11,"first_name":"Diana","last_name":"Billington"},
{"id":12,"first_name":"Udale","last_name":"Chesley"},
{"id":13,"first_name":"Kaitlin","last_name":"Blandamere"},
{"id":14,"first_name":"Erl","last_name":"Dymott"},
{"id":15,"first_name":"Robbin","last_name":"Geater"},
{"id":16,"first_name":"Wernher","last_name":"Waddingham"},
{"id":17,"first_name":"Dawna","last_name":"Handrek"},
{"id":18,"first_name":"Zara","last_name":"Mellon"},
{"id":19,"first_name":"Angeline","last_name":"Shuker"},
{"id":20,"first_name":"Austin","last_name":"Hardy"}]
  
}
